ulcarchetype/__init__.py
ulcarchetype/utils.py
ulcarchetype-0.2.dist-info/LICENSE
ulcarchetype-0.2.dist-info/METADATA
ulcarchetype-0.2.dist-info/WHEEL
ulcarchetype-0.2.dist-info/top_level.txt
ulcarchetype-0.2.dist-info/RECORD
