Metadata-Version: 2.1
Name: ulcarchetype
Version: 0.2
Summary: package to estimate uncertainty related to lca archetypes
Home-page: https://github.com/mfastudillo/ulcarchetype
Author: Miguel F. Astudillo
Author-email: migferast@gmail.com
License: LICENSE.txt
Platform: UNKNOWN
Classifier: Programming Language :: Python :: 3
Classifier: License :: OSI Approved :: BSD License
Classifier: Operating System :: OS Independent
Requires-Dist: pandas
Requires-Dist: brightway2
Requires-Dist: numpy
